{
  "resolvedId": "/Users/rezajafar/peakofeloquence-app/node_modules/@nuxt/ui-pro/modules/pro/runtime/components/global/CodeGroup.vue?nuxt_component=async&nuxt_component_name=CodeGroup&nuxt_component_export=default",
  "transforms": [
    {
      "name": "vite:load-fallback",
      "result": "<template>\n  <div :class=\"ui.wrapper\" v-bind=\"attrs\">\n    <div :class=\"ui.header\">\n      <button\n        v-for=\"(tab, index) in tabs\"\n        :key=\"index\"\n        tabindex=\"-1\"\n        :class=\"[ui.tab.base, selectedIndex === index ? ui.tab.active : ui.tab.inactive]\"\n        @click=\"selectedIndex = index\"\n      >\n        <ProseCodeIcon :icon=\"tab.icon\" :filename=\"tab.label\" :class=\"ui.tab.icon.base\" />\n        <span>{{ tab.label }}</span>\n      </button>\n    </div>\n\n    <component :is=\"selectedTab?.component\" :key=\"selectedIndex\" hide-header />\n  </div>\n</template>\n\n<script setup lang=\"ts\">\nimport type { PropType } from 'vue'\n\nconst config = {\n  wrapper: 'relative [&>div:last-child]:!my-0 [&>div:last-child]:!static my-5',\n  header: 'flex items-center gap-1 border border-gray-200 dark:border-gray-700 border-b-0 rounded-t-md overflow-hidden p-2',\n  tab: {\n    base: 'px-2 py-1.5 focus:outline-none text-gray-700 dark:text-gray-200 text-sm rounded-md flex items-center gap-1.5',\n    active: 'bg-gray-100 dark:bg-gray-800',\n    inactive: 'hover:bg-gray-50 dark:hover:bg-gray-800/50',\n    icon: {\n      base: ''\n    }\n  }\n}\n\ndefineOptions({\n  inheritAttrs: false\n})\n\nconst props = defineProps({\n  class: {\n    type: [String, Object, Array] as PropType<any>,\n    default: undefined\n  }\n})\n\nconst slots = useSlots()\nconst { ui, attrs } = useUI('content.codeGroup', undefined, config, toRef(props, 'class'), true)\n\nconst selectedIndex = ref(0)\ndefineExpose({ selectedIndex })\n\nfunction transformSlot (slot: any, index: number) {\n  if (typeof slot.type === 'symbol') {\n    return slot.children?.map(transformSlot)\n  }\n\n  return {\n    label: slot.props?.filename || slot.props?.label || `${index}`,\n    icon: slot.props?.icon,\n    component: slot\n  }\n}\n\n// Computed\n\nconst tabs = computed(() => slots.default?.()?.flatMap(transformSlot).filter(Boolean) || [])\n\nconst selectedTab = computed(() => tabs.value.find((_, index) => index === selectedIndex.value))\n</script>\n",
      "start": 1714180695354,
      "end": 1714180697097,
      "sourcemaps": null
    },
    {
      "name": "nuxt:layer-aliasing",
      "start": 1714180697097,
      "end": 1714180697097,
      "order": "pre"
    },
    {
      "name": "nuxt:server-devonly:transform",
      "start": 1714180697097,
      "end": 1714180697097,
      "order": "pre"
    },
    {
      "name": "content-slot",
      "start": 1714180697097,
      "end": 1714180697097,
      "order": "pre"
    },
    {
      "name": "nuxt:client-fallback-auto-id",
      "start": 1714180697097,
      "end": 1714180697097,
      "order": "pre"
    },
    {
      "name": "vite:css",
      "start": 1714180697097,
      "end": 1714180697097,
      "order": "normal"
    },
    {
      "name": "vite:esbuild",
      "start": 1714180697097,
      "end": 1714180697097,
      "order": "normal"
    },
    {
      "name": "vite:json",
      "start": 1714180697097,
      "end": 1714180697097,
      "order": "normal"
    },
    {
      "name": "vite:worker",
      "start": 1714180697097,
      "end": 1714180697097,
      "order": "normal"
    },
    {
      "name": "vite:vue",
      "result": "import _sfc_main from \"/Users/rezajafar/peakofeloquence-app/node_modules/@nuxt/ui-pro/modules/pro/runtime/components/global/CodeGroup.vue?vue&type=script&setup=true&lang.ts\";\nexport * from \"/Users/rezajafar/peakofeloquence-app/node_modules/@nuxt/ui-pro/modules/pro/runtime/components/global/CodeGroup.vue?vue&type=script&setup=true&lang.ts\";\nexport default _sfc_main;\n",
      "start": 1714180697097,
      "end": 1714180697109,
      "order": "normal",
      "sourcemaps": {
        "mappings": ""
      }
    },
    {
      "name": "vite:vue-jsx",
      "start": 1714180697109,
      "end": 1714180697109,
      "order": "normal"
    },
    {
      "name": "replace",
      "start": 1714180697109,
      "end": 1714180697109,
      "order": "normal"
    },
    {
      "name": "nuxt:remove-plugin-metadata",
      "start": 1714180697109,
      "end": 1714180697109,
      "order": "normal"
    },
    {
      "name": "nuxt:fonts:font-family-injection",
      "start": 1714180697109,
      "end": 1714180697109,
      "order": "normal"
    },
    {
      "name": "nuxt:chunk-error",
      "start": 1714180697109,
      "end": 1714180697109,
      "order": "normal"
    },
    {
      "name": "nuxt:components:imports",
      "result": "import { defineAsyncComponent } from \"vue\"\nexport default defineAsyncComponent(() => import(\"/Users/rezajafar/peakofeloquence-app/node_modules/@nuxt/ui-pro/modules/pro/runtime/components/global/CodeGroup.vue\").then(r => r[\"default\"] || r.default || r))",
      "start": 1714180697110,
      "end": 1714180697110,
      "order": "normal",
      "sourcemaps": null
    },
    {
      "name": "replace",
      "start": 1714180697110,
      "end": 1714180697110,
      "order": "normal"
    },
    {
      "name": "ssr-styles",
      "start": 1714180697110,
      "end": 1714180697110,
      "order": "normal"
    },
    {
      "name": "vite:define",
      "start": 1714180697110,
      "end": 1714180697110,
      "order": "normal"
    },
    {
      "name": "vite:css-post",
      "start": 1714180697110,
      "end": 1714180697110,
      "order": "normal"
    },
    {
      "name": "vite:build-html",
      "start": 1714180697110,
      "end": 1714180697110,
      "order": "normal"
    },
    {
      "name": "vite:worker-import-meta-url",
      "start": 1714180697110,
      "end": 1714180697110,
      "order": "normal"
    },
    {
      "name": "vite:asset-import-meta-url",
      "start": 1714180697110,
      "end": 1714180697110,
      "order": "normal"
    },
    {
      "name": "commonjs",
      "start": 1714180697110,
      "end": 1714180697110,
      "order": "normal"
    },
    {
      "name": "vite:dynamic-import-vars",
      "start": 1714180697110,
      "end": 1714180697111,
      "order": "normal"
    },
    {
      "name": "vite:import-glob",
      "start": 1714180697111,
      "end": 1714180697111,
      "order": "normal"
    },
    {
      "name": "nuxt:composable-keys",
      "start": 1714180697111,
      "end": 1714180697111,
      "order": "post"
    },
    {
      "name": "nuxt:imports-transform",
      "start": 1714180697111,
      "end": 1714180697111,
      "order": "post"
    },
    {
      "name": "unctx:transform",
      "start": 1714180697111,
      "end": 1714180697111,
      "order": "post"
    },
    {
      "name": "nuxt:pages-macros-transform",
      "start": 1714180697112,
      "end": 1714180697112,
      "order": "post"
    },
    {
      "name": "nuxt:runtime-paths-dep",
      "start": 1714180697112,
      "end": 1714180697112,
      "order": "post"
    },
    {
      "name": "nuxt:route-injection-plugin",
      "start": 1714180697112,
      "end": 1714180697112,
      "order": "post"
    },
    {
      "name": "nuxt:components-loader",
      "start": 1714180697113,
      "end": 1714180697113,
      "order": "post"
    },
    {
      "name": "nuxt:tree-shake-composables:transform",
      "start": 1714180697113,
      "end": 1714180697113,
      "order": "post"
    },
    {
      "name": "vite:build-import-analysis",
      "result": "import { __vitePreload } from \"\u0000vite/preload-helper.js\";import { defineAsyncComponent } from \"vue\"\nexport default defineAsyncComponent(() => __vitePreload(() => import(\"/Users/rezajafar/peakofeloquence-app/node_modules/@nuxt/ui-pro/modules/pro/runtime/components/global/CodeGroup.vue\"),__VITE_IS_MODERN__?\"__VITE_PRELOAD__\":void 0,import.meta.url).then(r => r[\"default\"] || r.default || r))",
      "start": 1714180697113,
      "end": 1714180697113,
      "order": "normal",
      "sourcemaps": null
    },
    {
      "name": "vite:reporter",
      "start": 1714180697113,
      "end": 1714180697113,
      "order": "normal"
    }
  ]
}
