{
  "resolvedId": "/Users/rezajafar/peakofeloquence-app/node_modules/@nuxt/ui-pro/modules/pro/runtime/app/router.options.ts",
  "transforms": [
    {
      "name": "vite:load-fallback",
      "result": "import type { RouterConfig } from '@nuxt/schema'\n\nfunction findHashPosition (hash: string): { el: any, behavior: ScrollBehavior, top: number } | undefined {\n  const el = document.querySelector(hash)\n  // vue-router does not incorporate scroll-margin-top on its own.\n  if (el) {\n    const top = parseFloat(getComputedStyle(el).scrollMarginTop)\n\n    return {\n      el: hash,\n      behavior: 'smooth',\n      top\n    }\n  }\n}\n\n// https://router.vuejs.org/api/#routeroptions\nexport default <RouterConfig>{\n  scrollBehavior (to, from, savedPosition) {\n    const nuxtApp = useNuxtApp()\n\n    if (history.state && history.state.stop) {\n      return\n    }\n    if (history.state && history.state.smooth) {\n      return {\n        el: history.state.smooth,\n        behavior: 'smooth'\n      }\n    }\n\n    // If history back\n    if (savedPosition) {\n      // Handle Suspense resolution\n      return new Promise((resolve) => {\n        nuxtApp.hooks.hookOnce('page:finish', () => {\n          setTimeout(() => resolve(savedPosition), 50)\n        })\n      })\n    }\n\n    // Scroll to heading on click\n    if (to.hash) {\n      return new Promise((resolve) => {\n        if (to.path === from.path) {\n          setTimeout(() => resolve(findHashPosition(to.hash)), 50)\n        } else {\n          nuxtApp.hooks.hookOnce('page:finish', () => {\n            setTimeout(() => resolve(findHashPosition(to.hash)), 50)\n          })\n        }\n      })\n    }\n\n    // Scroll to top of window\n    return { top: 0 }\n  }\n}\n",
      "start": 1714175001823,
      "end": 1714175001832,
      "sourcemaps": null
    },
    {
      "name": "nuxt:layer-aliasing",
      "start": 1714175001832,
      "end": 1714175001832,
      "order": "pre"
    },
    {
      "name": "nuxt:server-devonly:transform",
      "start": 1714175001832,
      "end": 1714175001832,
      "order": "pre"
    },
    {
      "name": "content-slot",
      "start": 1714175001832,
      "end": 1714175001832,
      "order": "pre"
    },
    {
      "name": "nuxt:client-fallback-auto-id",
      "start": 1714175001832,
      "end": 1714175001832,
      "order": "pre"
    },
    {
      "name": "vite:css",
      "start": 1714175001832,
      "end": 1714175001832,
      "order": "normal"
    },
    {
      "name": "vite:esbuild",
      "result": "function findHashPosition(hash) {\n  const el = document.querySelector(hash);\n  if (el) {\n    const top = parseFloat(getComputedStyle(el).scrollMarginTop);\n    return {\n      el: hash,\n      behavior: \"smooth\",\n      top\n    };\n  }\n}\nexport default {\n  scrollBehavior(to, from, savedPosition) {\n    const nuxtApp = useNuxtApp();\n    if (history.state && history.state.stop) {\n      return;\n    }\n    if (history.state && history.state.smooth) {\n      return {\n        el: history.state.smooth,\n        behavior: \"smooth\"\n      };\n    }\n    if (savedPosition) {\n      return new Promise((resolve) => {\n        nuxtApp.hooks.hookOnce(\"page:finish\", () => {\n          setTimeout(() => resolve(savedPosition), 50);\n        });\n      });\n    }\n    if (to.hash) {\n      return new Promise((resolve) => {\n        if (to.path === from.path) {\n          setTimeout(() => resolve(findHashPosition(to.hash)), 50);\n        } else {\n          nuxtApp.hooks.hookOnce(\"page:finish\", () => {\n            setTimeout(() => resolve(findHashPosition(to.hash)), 50);\n          });\n        }\n      });\n    }\n    return { top: 0 };\n  }\n};\n",
      "start": 1714175001832,
      "end": 1714175002094,
      "order": "normal",
      "sourcemaps": {
        "version": 3,
        "sources": [
          "/Users/rezajafar/peakofeloquence-app/node_modules/@nuxt/ui-pro/modules/pro/runtime/app/router.options.ts"
        ],
        "sourcesContent": [
          "import type { RouterConfig } from '@nuxt/schema'\n\nfunction findHashPosition (hash: string): { el: any, behavior: ScrollBehavior, top: number } | undefined {\n  const el = document.querySelector(hash)\n  // vue-router does not incorporate scroll-margin-top on its own.\n  if (el) {\n    const top = parseFloat(getComputedStyle(el).scrollMarginTop)\n\n    return {\n      el: hash,\n      behavior: 'smooth',\n      top\n    }\n  }\n}\n\n// https://router.vuejs.org/api/#routeroptions\nexport default <RouterConfig>{\n  scrollBehavior (to, from, savedPosition) {\n    const nuxtApp = useNuxtApp()\n\n    if (history.state && history.state.stop) {\n      return\n    }\n    if (history.state && history.state.smooth) {\n      return {\n        el: history.state.smooth,\n        behavior: 'smooth'\n      }\n    }\n\n    // If history back\n    if (savedPosition) {\n      // Handle Suspense resolution\n      return new Promise((resolve) => {\n        nuxtApp.hooks.hookOnce('page:finish', () => {\n          setTimeout(() => resolve(savedPosition), 50)\n        })\n      })\n    }\n\n    // Scroll to heading on click\n    if (to.hash) {\n      return new Promise((resolve) => {\n        if (to.path === from.path) {\n          setTimeout(() => resolve(findHashPosition(to.hash)), 50)\n        } else {\n          nuxtApp.hooks.hookOnce('page:finish', () => {\n            setTimeout(() => resolve(findHashPosition(to.hash)), 50)\n          })\n        }\n      })\n    }\n\n    // Scroll to top of window\n    return { top: 0 }\n  }\n}\n"
        ],
        "mappings": "AAEA,SAAS,iBAAkB,MAA8E;AACvG,QAAM,KAAK,SAAS,cAAc,IAAI;AAEtC,MAAI,IAAI;AACN,UAAM,MAAM,WAAW,iBAAiB,EAAE,EAAE,eAAe;AAE3D,WAAO;AAAA,MACL,IAAI;AAAA,MACJ,UAAU;AAAA,MACV;AAAA,IACF;AAAA,EACF;AACF;AAGA,eAA6B;AAAA,EAC3B,eAAgB,IAAI,MAAM,eAAe;AACvC,UAAM,UAAU,WAAW;AAE3B,QAAI,QAAQ,SAAS,QAAQ,MAAM,MAAM;AACvC;AAAA,IACF;AACA,QAAI,QAAQ,SAAS,QAAQ,MAAM,QAAQ;AACzC,aAAO;AAAA,QACL,IAAI,QAAQ,MAAM;AAAA,QAClB,UAAU;AAAA,MACZ;AAAA,IACF;AAGA,QAAI,eAAe;AAEjB,aAAO,IAAI,QAAQ,CAAC,YAAY;AAC9B,gBAAQ,MAAM,SAAS,eAAe,MAAM;AAC1C,qBAAW,MAAM,QAAQ,aAAa,GAAG,EAAE;AAAA,QAC7C,CAAC;AAAA,MACH,CAAC;AAAA,IACH;AAGA,QAAI,GAAG,MAAM;AACX,aAAO,IAAI,QAAQ,CAAC,YAAY;AAC9B,YAAI,GAAG,SAAS,KAAK,MAAM;AACzB,qBAAW,MAAM,QAAQ,iBAAiB,GAAG,IAAI,CAAC,GAAG,EAAE;AAAA,QACzD,OAAO;AACL,kBAAQ,MAAM,SAAS,eAAe,MAAM;AAC1C,uBAAW,MAAM,QAAQ,iBAAiB,GAAG,IAAI,CAAC,GAAG,EAAE;AAAA,UACzD,CAAC;AAAA,QACH;AAAA,MACF,CAAC;AAAA,IACH;AAGA,WAAO,EAAE,KAAK,EAAE;AAAA,EAClB;AACF;",
        "names": []
      }
    },
    {
      "name": "vite:json",
      "start": 1714175002094,
      "end": 1714175002094,
      "order": "normal"
    },
    {
      "name": "vite:worker",
      "start": 1714175002094,
      "end": 1714175002094,
      "order": "normal"
    },
    {
      "name": "vite:vue",
      "start": 1714175002094,
      "end": 1714175002094,
      "order": "normal"
    },
    {
      "name": "vite:vue-jsx",
      "start": 1714175002094,
      "end": 1714175002094,
      "order": "normal"
    },
    {
      "name": "replace",
      "start": 1714175002094,
      "end": 1714175002094,
      "order": "normal"
    },
    {
      "name": "nuxt:remove-plugin-metadata",
      "start": 1714175002094,
      "end": 1714175002094,
      "order": "normal"
    },
    {
      "name": "nuxt:fonts:font-family-injection",
      "start": 1714175002094,
      "end": 1714175002094,
      "order": "normal"
    },
    {
      "name": "nuxt:chunk-error",
      "start": 1714175002094,
      "end": 1714175002094,
      "order": "normal"
    },
    {
      "name": "nuxt:components:imports",
      "start": 1714175002094,
      "end": 1714175002094,
      "order": "normal"
    },
    {
      "name": "replace",
      "start": 1714175002094,
      "end": 1714175002094,
      "order": "normal"
    },
    {
      "name": "ssr-styles",
      "start": 1714175002094,
      "end": 1714175002094,
      "order": "normal"
    },
    {
      "name": "vite:define",
      "start": 1714175002094,
      "end": 1714175002094,
      "order": "normal"
    },
    {
      "name": "vite:css-post",
      "start": 1714175002094,
      "end": 1714175002094,
      "order": "normal"
    },
    {
      "name": "vite:build-html",
      "start": 1714175002094,
      "end": 1714175002094,
      "order": "normal"
    },
    {
      "name": "vite:worker-import-meta-url",
      "start": 1714175002094,
      "end": 1714175002094,
      "order": "normal"
    },
    {
      "name": "vite:asset-import-meta-url",
      "start": 1714175002094,
      "end": 1714175002094,
      "order": "normal"
    },
    {
      "name": "commonjs",
      "start": 1714175002094,
      "end": 1714175002094,
      "order": "normal"
    },
    {
      "name": "vite:dynamic-import-vars",
      "start": 1714175002094,
      "end": 1714175002094,
      "order": "normal"
    },
    {
      "name": "vite:import-glob",
      "start": 1714175002094,
      "end": 1714175002094,
      "order": "normal"
    },
    {
      "name": "nuxt:composable-keys",
      "start": 1714175002094,
      "end": 1714175002094,
      "order": "post"
    },
    {
      "name": "nuxt:imports-transform",
      "result": "import { useNuxtApp } from '#app/nuxt';\nfunction findHashPosition(hash) {\n  const el = document.querySelector(hash);\n  if (el) {\n    const top = parseFloat(getComputedStyle(el).scrollMarginTop);\n    return {\n      el: hash,\n      behavior: \"smooth\",\n      top\n    };\n  }\n}\nexport default {\n  scrollBehavior(to, from, savedPosition) {\n    const nuxtApp = useNuxtApp();\n    if (history.state && history.state.stop) {\n      return;\n    }\n    if (history.state && history.state.smooth) {\n      return {\n        el: history.state.smooth,\n        behavior: \"smooth\"\n      };\n    }\n    if (savedPosition) {\n      return new Promise((resolve) => {\n        nuxtApp.hooks.hookOnce(\"page:finish\", () => {\n          setTimeout(() => resolve(savedPosition), 50);\n        });\n      });\n    }\n    if (to.hash) {\n      return new Promise((resolve) => {\n        if (to.path === from.path) {\n          setTimeout(() => resolve(findHashPosition(to.hash)), 50);\n        } else {\n          nuxtApp.hooks.hookOnce(\"page:finish\", () => {\n            setTimeout(() => resolve(findHashPosition(to.hash)), 50);\n          });\n        }\n      });\n    }\n    return { top: 0 };\n  }\n};\n",
      "start": 1714175002095,
      "end": 1714175002095,
      "order": "post",
      "sourcemaps": {
        "version": 3,
        "sources": [
          ""
        ],
        "names": [],
        "mappings": ";AAAA,CAAC,CAAC,CAAC,CAAC,CAAC,CAAC,CAAC,CAAC,CAAC,CAAC,CAAC,CAAC,CAAC,CAAC,CAAC,CAAC,CAAC,CAAC,CAAC,CAAC,CAAC,CAAC,CAAC,CAAC,CAAC,CAAC,CAAC,CAAC,CAAC,CAAC,CAAC,CAAC,CAAC;AACjC,CAAC,CAAC,CAAC,CAAC,CAAC,CAAC,CAAC,CAAC,CAAC,CAAC,CAAC,CAAC,CAAC,CAAC,CAAC,CAAC,CAAC,CAAC,CAAC,CAAC,CAAC,CAAC,CAAC,CAAC,CAAC,CAAC,CAAC,CAAC,CAAC,CAAC,CAAC,CAAC,CAAC,CAAC,CAAC,CAAC,CAAC,CAAC,CAAC,CAAC,CAAC,CAAC;AAC1C,CAAC,CAAC,CAAC,CAAC,CAAC,CAAC,CAAC,CAAC,CAAC,CAAC,CAAC;AACX,CAAC,CAAC,CAAC,CAAC,CAAC,CAAC,CAAC,CAAC,CAAC,CAAC,CAAC,CAAC,CAAC,CAAC,CAAC,CAAC,CAAC,CAAC,CAAC,CAAC,CAAC,CAAC,CAAC,CAAC,CAAC,CAAC,CAAC,CAAC,CAAC,CAAC,CAAC,CAAC,CAAC,CAAC,CAAC,CAAC,CAAC,CAAC,CAAC,CAAC,CAAC,CAAC,CAAC,CAAC,CAAC,CAAC,CAAC,CAAC,CAAC,CAAC,CAAC,CAAC,CAAC,CAAC,CAAC,CAAC,CAAC,CAAC,CAAC,CAAC,CAAC,CAAC,CAAC,CAAC,CAAC;AACjE,CAAC,CAAC,CAAC,CAAC,CAAC,CAAC,CAAC,CAAC,CAAC,CAAC,CAAC,CAAC;AACZ,CAAC,CAAC,CAAC,CAAC,CAAC,CAAC,CAAC,CAAC,CAAC,CAAC,CAAC,CAAC,CAAC,CAAC,CAAC;AACf,CAAC,CAAC,CAAC,CAAC,CAAC,CAAC,CAAC,CAAC,CAAC,CAAC,CAAC,CAAC,CAAC,CAAC,CAAC,CAAC,CAAC,CAAC,CAAC,CAAC,CAAC,CAAC,CAAC,CAAC,CAAC;AACzB,CAAC,CAAC,CAAC,CAAC,CAAC,CAAC,CAAC,CAAC,CAAC;AACT,CAAC,CAAC,CAAC,CAAC,CAAC,CAAC;AACN,CAAC,CAAC,CAAC;AACH,CAAC;AACD,CAAC,CAAC,CAAC,CAAC,CAAC,CAAC,CAAC,CAAC,CAAC,CAAC,CAAC,CAAC,CAAC,CAAC,CAAC,CAAC;AAChB,CAAC,CAAC,CAAC,CAAC,CAAC,CAAC,CAAC,CAAC,CAAC,CAAC,CAAC,CAAC,CAAC,CAAC,CAAC,CAAC,CAAC,CAAC,CAAC,CAAC,CAAC,CAAC,CAAC,CAAC,CAAC,CAAC,CAAC,CAAC,CAAC,CAAC,CAAC,CAAC,CAAC,CAAC,CAAC,CAAC,CAAC,CAAC,CAAC,CAAC,CAAC,CAAC,CAAC;AAC3C,CAAC,CAAC,CAAC,CAAC,CAAC,CAAC,CAAC,CAAC,CAAC,CAAC,CAAC,CAAC,CAAC,CAAC,CAAC,CAAC,CAAC,CAAC,CAAC,CAAC,CAAC,CAAC,CAAC,CAAC,CAAC,CAAC,CAAC,CAAC,CAAC,CAAC,CAAC,CAAC,CAAC;AACjC,CAAC,CAAC,CAAC,CAAC,CAAC,CAAC,CAAC,CAAC,CAAC,CAAC,CAAC,CAAC,CAAC,CAAC,CAAC,CAAC,CAAC,CAAC,CAAC,CAAC,CAAC,CAAC,CAAC,CAAC,CAAC,CAAC,CAAC,CAAC,CAAC,CAAC,CAAC,CAAC,CAAC,CAAC,CAAC,CAAC,CAAC,CAAC,CAAC,CAAC,CAAC,CAAC,CAAC,CAAC,CAAC,CAAC;AAC9C,CAAC,CAAC,CAAC,CAAC,CAAC,CAAC,CAAC,CAAC,CAAC,CAAC,CAAC,CAAC,CAAC;AACb,CAAC,CAAC,CAAC,CAAC,CAAC;AACL,CAAC,CAAC,CAAC,CAAC,CAAC,CAAC,CAAC,CAAC,CAAC,CAAC,CAAC,CAAC,CAAC,CAAC,CAAC,CAAC,CAAC,CAAC,CAAC,CAAC,CAAC,CAAC,CAAC,CAAC,CAAC,CAAC,CAAC,CAAC,CAAC,CAAC,CAAC,CAAC,CAAC,CAAC,CAAC,CAAC,CAAC,CAAC,CAAC,CAAC,CAAC,CAAC,CAAC,CAAC,CAAC,CAAC,CAAC,CAAC;AAChD,CAAC,CAAC,CAAC,CAAC,CAAC,CAAC,CAAC,CAAC,CAAC,CAAC,CAAC,CAAC,CAAC,CAAC;AACd,CAAC,CAAC,CAAC,CAAC,CAAC,CAAC,CAAC,CAAC,CAAC,CAAC,CAAC,CAAC,CAAC,CAAC,CAAC,CAAC,CAAC,CAAC,CAAC,CAAC,CAAC,CAAC,CAAC,CAAC,CAAC,CAAC,CAAC,CAAC,CAAC,CAAC,CAAC,CAAC,CAAC;AACjC,CAAC,CAAC,CAAC,CAAC,CAAC,CAAC,CAAC,CAAC,CAAC,CAAC,CAAC,CAAC,CAAC,CAAC,CAAC,CAAC,CAAC,CAAC,CAAC,CAAC,CAAC,CAAC,CAAC,CAAC,CAAC,CAAC;AAC1B,CAAC,CAAC,CAAC,CAAC,CAAC,CAAC,CAAC,CAAC;AACR,CAAC,CAAC,CAAC,CAAC,CAAC;AACL,CAAC,CAAC,CAAC,CAAC,CAAC,CAAC,CAAC,CAAC,CAAC,CAAC,CAAC,CAAC,CAAC,CAAC,CAAC,CAAC,CAAC,CAAC,CAAC,CAAC,CAAC,CAAC,CAAC,CAAC;AACxB,CAAC,CAAC,CAAC,CAAC,CAAC,CAAC,CAAC,CAAC,CAAC,CAAC,CAAC,CAAC,CAAC,CAAC,CAAC,CAAC,CAAC,CAAC,CAAC,CAAC,CAAC,CAAC,CAAC,CAAC,CAAC,CAAC,CAAC,CAAC,CAAC,CAAC,CAAC,CAAC,CAAC,CAAC,CAAC,CAAC,CAAC,CAAC,CAAC;AACvC,CAAC,CAAC,CAAC,CAAC,CAAC,CAAC,CAAC,CAAC,CAAC,CAAC,CAAC,CAAC,CAAC,CAAC,CAAC,CAAC,CAAC,CAAC,CAAC,CAAC,CAAC,CAAC,CAAC,CAAC,CAAC,CAAC,CAAC,CAAC,CAAC,CAAC,CAAC,CAAC,CAAC,CAAC,CAAC,CAAC,CAAC,CAAC,CAAC,CAAC,CAAC,CAAC,CAAC,CAAC,CAAC,CAAC,CAAC,CAAC,CAAC,CAAC,CAAC,CAAC,CAAC;AACrD,CAAC,CAAC,CAAC,CAAC,CAAC,CAAC,CAAC,CAAC,CAAC,CAAC,CAAC,CAAC,CAAC,CAAC,CAAC,CAAC,CAAC,CAAC,CAAC,CAAC,CAAC,CAAC,CAAC,CAAC,CAAC,CAAC,CAAC,CAAC,CAAC,CAAC,CAAC,CAAC,CAAC,CAAC,CAAC,CAAC,CAAC,CAAC,CAAC,CAAC,CAAC,CAAC,CAAC,CAAC,CAAC,CAAC,CAAC,CAAC,CAAC,CAAC,CAAC,CAAC,CAAC,CAAC,CAAC;AACvD,CAAC,CAAC,CAAC,CAAC,CAAC,CAAC,CAAC,CAAC,CAAC,CAAC,CAAC;AACX,CAAC,CAAC,CAAC,CAAC,CAAC,CAAC,CAAC,CAAC,CAAC;AACT,CAAC,CAAC,CAAC,CAAC,CAAC;AACL,CAAC,CAAC,CAAC,CAAC,CAAC,CAAC,CAAC,CAAC,CAAC,CAAC,CAAC,CAAC,CAAC,CAAC,CAAC,CAAC,CAAC,CAAC;AAClB,CAAC,CAAC,CAAC,CAAC,CAAC,CAAC,CAAC,CAAC,CAAC,CAAC,CAAC,CAAC,CAAC,CAAC,CAAC,CAAC,CAAC,CAAC,CAAC,CAAC,CAAC,CAAC,CAAC,CAAC,CAAC,CAAC,CAAC,CAAC,CAAC,CAAC,CAAC,CAAC,CAAC,CAAC,CAAC,CAAC,CAAC,CAAC,CAAC;AACvC,CAAC,CAAC,CAAC,CAAC,CAAC,CAAC,CAAC,CAAC,CAAC,CAAC,CAAC,CAAC,CAAC,CAAC,CAAC,CAAC,CAAC,CAAC,CAAC,CAAC,CAAC,CAAC,CAAC,CAAC,CAAC,CAAC,CAAC,CAAC,CAAC,CAAC,CAAC,CAAC,CAAC,CAAC,CAAC,CAAC;AACpC,CAAC,CAAC,CAAC,CAAC,CAAC,CAAC,CAAC,CAAC,CAAC,CAAC,CAAC,CAAC,CAAC,CAAC,CAAC,CAAC,CAAC,CAAC,CAAC,CAAC,CAAC,CAAC,CAAC,CAAC,CAAC,CAAC,CAAC,CAAC,CAAC,CAAC,CAAC,CAAC,CAAC,CAAC,CAAC,CAAC,CAAC,CAAC,CAAC,CAAC,CAAC,CAAC,CAAC,CAAC,CAAC,CAAC,CAAC,CAAC,CAAC,CAAC,CAAC,CAAC,CAAC,CAAC,CAAC,CAAC,CAAC,CAAC,CAAC,CAAC,CAAC,CAAC,CAAC,CAAC,CAAC,CAAC,CAAC;AACnE,CAAC,CAAC,CAAC,CAAC,CAAC,CAAC,CAAC,CAAC,CAAC,CAAC,CAAC,CAAC,CAAC,CAAC,CAAC,CAAC;AAChB,CAAC,CAAC,CAAC,CAAC,CAAC,CAAC,CAAC,CAAC,CAAC,CAAC,CAAC,CAAC,CAAC,CAAC,CAAC,CAAC,CAAC,CAAC,CAAC,CAAC,CAAC,CAAC,CAAC,CAAC,CAAC,CAAC,CAAC,CAAC,CAAC,CAAC,CAAC,CAAC,CAAC,CAAC,CAAC,CAAC,CAAC,CAAC,CAAC,CAAC,CAAC,CAAC,CAAC,CAAC,CAAC,CAAC,CAAC,CAAC,CAAC,CAAC,CAAC,CAAC,CAAC,CAAC,CAAC;AACvD,CAAC,CAAC,CAAC,CAAC,CAAC,CAAC,CAAC,CAAC,CAAC,CAAC,CAAC,CAAC,CAAC,CAAC,CAAC,CAAC,CAAC,CAAC,CAAC,CAAC,CAAC,CAAC,CAAC,CAAC,CAAC,CAAC,CAAC,CAAC,CAAC,CAAC,CAAC,CAAC,CAAC,CAAC,CAAC,CAAC,CAAC,CAAC,CAAC,CAAC,CAAC,CAAC,CAAC,CAAC,CAAC,CAAC,CAAC,CAAC,CAAC,CAAC,CAAC,CAAC,CAAC,CAAC,CAAC,CAAC,CAAC,CAAC,CAAC,CAAC,CAAC,CAAC,CAAC,CAAC,CAAC,CAAC,CAAC,CAAC,CAAC;AACrE,CAAC,CAAC,CAAC,CAAC,CAAC,CAAC,CAAC,CAAC,CAAC,CAAC,CAAC,CAAC,CAAC;AACb,CAAC,CAAC,CAAC,CAAC,CAAC,CAAC,CAAC,CAAC,CAAC;AACT,CAAC,CAAC,CAAC,CAAC,CAAC,CAAC,CAAC,CAAC,CAAC;AACT,CAAC,CAAC,CAAC,CAAC,CAAC;AACL,CAAC,CAAC,CAAC,CAAC,CAAC,CAAC,CAAC,CAAC,CAAC,CAAC,CAAC,CAAC,CAAC,CAAC,CAAC,CAAC,CAAC,CAAC,CAAC,CAAC,CAAC,CAAC;AACtB,CAAC,CAAC,CAAC;AACH,CAAC,CAAC;"
      }
    },
    {
      "name": "unctx:transform",
      "start": 1714175002095,
      "end": 1714175002095,
      "order": "post"
    },
    {
      "name": "nuxt:pages-macros-transform",
      "start": 1714175002095,
      "end": 1714175002095,
      "order": "post"
    },
    {
      "name": "nuxt:runtime-paths-dep",
      "start": 1714175002095,
      "end": 1714175002095,
      "order": "post"
    },
    {
      "name": "nuxt:route-injection-plugin",
      "start": 1714175002095,
      "end": 1714175002095,
      "order": "post"
    },
    {
      "name": "nuxt:components-loader",
      "start": 1714175002095,
      "end": 1714175002095,
      "order": "post"
    },
    {
      "name": "nuxt:tree-shake-composables:transform",
      "start": 1714175002095,
      "end": 1714175002095,
      "order": "post"
    },
    {
      "name": "vite:build-import-analysis",
      "start": 1714175002095,
      "end": 1714175002095,
      "order": "normal"
    },
    {
      "name": "vite:reporter",
      "start": 1714175002095,
      "end": 1714175002095,
      "order": "normal"
    }
  ]
}
